[{"date":"2021-05-18T00:00:00Z","event":"http://www.wikidata.org/entity/Q68293252"},{"date":"2021-05-15T00:00:00Z","event":"http://www.wikidata.org/entity/Q76763729","eventLabel":"Chilean municipal elections, 2021"},{"date":"2021-06-06T00:00:00Z","event":"http://www.wikidata.org/entity/Q96182806","eventLabel":"2018 general elections in Chihuahua"},{"date":"2021-06-02T00:00:00Z","event":"http://www.wikidata.org/entity/Q97344629","eventLabel":"ECAS 2021"},{"date":"2021-05-31T00:00:00Z","event":"http://www.wikidata.org/entity/Q102274071","eventLabel":"The 23rd Nordic Conference on Computational Linguistics"},{"date":"2021-06-06T00:00:00Z","event":"http://www.wikidata.org/entity/Q102360510","eventLabel":"ESWC 2021"},{"date":"2021-06-01T00:00:00Z","event":"http://www.wikidata.org/entity/Q104881876","eventLabel":"2021 New Mexico's 1st congressional district special election"},{"date":"2021-05-27T00:00:00Z","event":"http://www.wikidata.org/entity/Q106603523","eventLabel":"Wikidata Lab XXIX"},{"date":"2021-05-18T00:00:00Z","event":"http://www.wikidata.org/entity/Q106727158","eventLabel":"IAIA21"},{"date":"2021-06-01T00:00:00Z","event":"http://www.wikidata.org/entity/Q106788884","eventLabel":"Natural objects of Estonia"}]
